namelib/__init__.py
namelib/core.py
namelib-0.0.0.dist-info/LICENSE.md
namelib-0.0.0.dist-info/METADATA
namelib-0.0.0.dist-info/WHEEL
namelib-0.0.0.dist-info/top_level.txt
namelib-0.0.0.dist-info/RECORD
