Metadata-Version: 2.1
Name: namelib
Version: 0.0.0
Home-page: https://github.com/harttraveller/namelib
Author: Hart Traveller
License: MIT
License-File: LICENSE.md
Requires-Dist: names-dataset
